confetti_engine/__init__.py
confetti_engine/confetti.py
confetti_engine/py.typed
confetti_engine-0.1.0rc1.dist-info/LICENSE
confetti_engine-0.1.0rc1.dist-info/METADATA
confetti_engine-0.1.0rc1.dist-info/WHEEL
confetti_engine-0.1.0rc1.dist-info/top_level.txt
confetti_engine-0.1.0rc1.dist-info/RECORD
