Metadata-Version: 2.1
Name: confetti-engine
Version: 0.1.0rc1
Summary: Build amazing terminal games with a simple and light codebase allowing you to focus on the game, not the packages
Author: Adam Garza
License: MIT
Project-URL: Homepage, https://github.com/TVRework/Confetti
Project-URL: Documentation, https://confetti-en.vercel.app
Project-URL: Bug Reports, https://github.com/TVRework/Confetti/issues
Platform: unix
Platform: linux
Platform: osx
Platform: cygwin
Classifier: Programming Language :: Python :: 3
Classifier: Programming Language :: Python :: 3 :: Only
Classifier: Programming Language :: Python :: 3.8
Classifier: Programming Language :: Python :: 3.9
Classifier: Programming Language :: Python :: 3.11
Requires-Python: >=3.8
License-File: LICENSE
Requires-Dist: attrs (~=23.1.0)
Provides-Extra: testing
Requires-Dist: flake8 (==6.1.0) ; extra == 'testing'
Requires-Dist: tox (==4.6.4) ; extra == 'testing'
Requires-Dist: pytest (==7.4.0) ; extra == 'testing'
Requires-Dist: pytest-cov (==4.1.0) ; extra == 'testing'
Requires-Dist: mypy (==1.4.1) ; extra == 'testing'
